LICENSE.txt
README.md
setup.cfg
setup.py
elsolver/__init__.py
elsolver/solver.py
elsolver.egg-info/PKG-INFO
elsolver.egg-info/SOURCES.txt
elsolver.egg-info/dependency_links.txt
elsolver.egg-info/requires.txt
elsolver.egg-info/top_level.txt