Metadata-Version: 2.1
Name: elsolver
Version: 0.10
Summary: Solver for Euler-Lagrange equations of a system using only its lagrangian
Home-page: https://github.com/Erneh/elsolver
Download-URL: https://github.com/Erneh/elsolver/archive/refs/tags/v010.tar.gz
Author: Joan Ernest Pérez
Author-email: ernestpech11@gmail.com
License: GPL-3.0-only
Keywords: PHYSICS,EULER-LAGRANGE,SIMULATION
Classifier: Development Status :: 3 - Alpha
Classifier: Programming Language :: Python :: 3
Classifier: Programming Language :: Python :: 3.11
Classifier: Programming Language :: Python :: 3.7
Classifier: Programming Language :: Python :: 3.8
Classifier: Programming Language :: Python :: 3.9
Classifier: Programming Language :: Python :: 3.10
Classifier: Programming Language :: Python :: 3.11
License-File: LICENSE.txt
